mishkal/__init__.py
mishkal/hebrew.py
mishkal/lexicon.py
mishkal/log.py
mishkal/phonemize.py
mishkal/utils.py
mishkal/variants.py
mishkal/data/kamatz_katan.json
mishkal/data/rashej_tevot.json
mishkal/data/special.json
mishkal/data/symbols.json
mishkal/expander/__init__.py
mishkal/expander/dates.py
mishkal/expander/dictionary.py
mishkal/expander/number_names.py
mishkal/expander/numbers.py
mishkal/expander/time_to_word.py
mishkal_hebrew-0.3.7.dist-info/METADATA
mishkal_hebrew-0.3.7.dist-info/WHEEL
mishkal_hebrew-0.3.7.dist-info/licenses/LICENSE
mishkal_hebrew-0.3.7.dist-info/RECORD
